[
  {
    "url": "https://nickystore.biz.id/anime/NICKY-Ml3gr0.jpg"
  },
  {
    "url": "https://nickystore.biz.id/anime/NICKY-CTFIMS.jpg"
  },
  {
    "url": "https://nickystore.biz.id/anime/NICKY-Dy6TcU.jpg"
  },
  {
    "url": "https://nickystore.biz.id/anime/NICKY-389Ai7.jpg"
  },
  {
    "url": "https://nickystore.biz.id/anime/NICKY-7SEtu4.jpg"
  },
  {
    "url": "https://nickystore.biz.id/anime/NICKY-zUG4aQ.jpg"
  },
  {
    "url": "https://nickystore.biz.id/anime/NICKY-tqIR9c.jpg"
  },
  {
    "url": "https://nickystore.biz.id/anime/NICKY-bMakPT.jpg"
  },
  {
    "url": "https://nickystore.biz.id/anime/NICKY-FsxNWp.jpg"
  },
  {
    "url": "https://nickystore.biz.id/anime/NICKY-Mf5nbV.jpg"
  },
  {
    "url": "https://nickystore.biz.id/anime/NICKY-mrHw3W.jpg"
  },
  {
    "url": "https://nickystore.biz.id/anime/NICKY-QJ9Cwt.jpg"
  },
  {
    "url": "https://nickystore.biz.id/anime/NICKY-ngLkEa.jpg"
  },
  {
    "url": "https://nickystore.biz.id/anime/NICKY-jrRbuS.jpg"
  },
  {
    "url": "https://nickystore.biz.id/anime/NICKY-Fi8Dph.jpg"
  },
  {
    "url": "https://nickystore.biz.id/anime/NICKY-OrQpVo.jpg"
  },
  {
    "url": "https://nickystore.biz.id/anime/NICKY-OSTiYh.jpg"
  },
  {
    "url": "https://nickystore.biz.id/anime/NICKY-0J9VTz.jpg"
  },
  {
    "url": "https://nickystore.biz.id/anime/NICKY-HFLIKZ.jpg"
  },
  {
    "url": "https://nickystore.biz.id/anime/NICKY-PuOUse.jpg"
  },
  {
    "url": "https://nickystore.biz.id/anime/NICKY-XkzsB0.jpg"
  },
  {
    "url": "https://nickystore.biz.id/anime/NICKY-wPu4N8.jpg"
  },
  {
    "url": "https://nickystore.biz.id/anime/NICKY-ACXbvu.jpg"
  },
  {
    "url": "https://nickystore.biz.id/anime/NICKY-ZQNSxE.jpg"
  },
  {
    "url": "https://nickystore.biz.id/anime/NICKY-fnGmHa.jpg"
  },
  {
    "url": "https://nickystore.biz.id/anime/NICKY-NYCOAr.jpg"
  },
  {
    "url": "https://nickystore.biz.id/anime/NICKY-5o2Nfd.jpg"
  },
  {
    "url": "https://nickystore.biz.id/anime/NICKY-rDzvsU.jpg"
  },
  {
    "url": "https://nickystore.biz.id/anime/NICKY-Oz7BNt.jpg"
  },
  {
    "url": "https://nickystore.biz.id/anime/NICKY-WzMjeV.jpg"
  },
  {
    "url": "https://nickystore.biz.id/anime/NICKY-mN1wPg.jpg"
  },
  {
    "url": "https://nickystore.biz.id/anime/NICKY-MAgIqs.jpg"
  },
  {
    "url": "https://nickystore.biz.id/anime/NICKY-ogNYAl.jpg"
  },
  {
    "url": "https://nickystore.biz.id/anime/NICKY-04Bvsw.jpg"
  },
  {
    "url": "https://nickystore.biz.id/anime/NICKY-MgKsIL.jpg"
  },
  {
    "url": "https://nickystore.biz.id/anime/NICKY-zUnCpv.jpg"
  },
  {
    "url": "https://nickystore.biz.id/anime/NICKY-wOSnzy.jpg"
  },
  {
    "url": "https://nickystore.biz.id/anime/NICKY-JpvjSF.jpg"
  },
  {
    "url": "https://nickystore.biz.id/anime/NICKY-ni4TpH.jpg"
  },
  {
    "url": "https://nickystore.biz.id/anime/NICKY-7W2leN.jpg"
  },
  {
    "url": "https://nickystore.biz.id/anime/NICKY-k9VdBD.jpg"
  },
  {
    "url": "https://nickystore.biz.id/anime/NICKY-wJyCIh.jpg"
  },
  {
    "url": "https://nickystore.biz.id/anime/NICKY-ijR7nH.jpg"
  },
  {
    "url": "https://nickystore.biz.id/anime/NICKY-MPj2si.jpg"
  },
  {
    "url": "https://nickystore.biz.id/anime/NICKY-X68C2K.jpg"
  },
  {
    "url": "https://nickystore.biz.id/anime/NICKY-8lBgwU.jpg"
  },
  {
    "url": "https://nickystore.biz.id/anime/NICKY-lkG1ZW.jpg"
  },
  {
    "url": "https://nickystore.biz.id/anime/NICKY-c85zuO.jpg"
  },
  {
    "url": "https://nickystore.biz.id/anime/NICKY-guB95r.jpg"
  },
  {
    "url": "https://nickystore.biz.id/anime/NICKY-l63rtp.jpg"
  },
  {
    "url": "https://nickystore.biz.id/anime/NICKY-sQk13y.jpg"
  },
  {
    "url": "https://nickystore.biz.id/anime/NICKY-lmN0Eh.jpg"
  },
  {
    "url": "https://nickystore.biz.id/anime/NICKY-U4r2YF.jpg"
  },
  {
    "url": "https://nickystore.biz.id/anime/NICKY-9sk8SD.jpg"
  },
  {
    "url": "https://nickystore.biz.id/anime/NICKY-guHo2t.jpg"
  },
  {
    "url": "https://nickystore.biz.id/anime/NICKY-nGg1jR.jpg"
  },
  {
    "url": "https://nickystore.biz.id/anime/NICKY-7ROue5.jpg"
  },
  {
    "url": "https://nickystore.biz.id/anime/NICKY-QlDd27.jpg"
  },
  {
    "url": "https://nickystore.biz.id/anime/NICKY-94DNX7.jpg"
  },
  {
    "url": "https://nickystore.biz.id/anime/NICKY-S4uhZB.jpg"
  },
  {
    "url": "https://nickystore.biz.id/anime/NICKY-eykG3O.jpg"
  },
  {
    "url": "https://nickystore.biz.id/anime/NICKY-m7TDyJ.jpg"
  },
  {
    "url": "https://nickystore.biz.id/anime/NICKY-jBwd2Z.jpg"
  },
  {
    "url": "https://nickystore.biz.id/anime/NICKY-M2TiAz.jpg"
  },
  {
    "url": "https://nickystore.biz.id/anime/NICKY-0iwf3l.jpg"
  },
  {
    "url": "https://nickystore.biz.id/anime/NICKY-B4xRXo.jpg"
  },
  {
    "url": "https://nickystore.biz.id/anime/NICKY-Kjkwzx.jpg"
  },
  {
    "url": "https://nickystore.biz.id/anime/NICKY-NC2ki3.jpg"
  },
  {
    "url": "https://nickystore.biz.id/anime/NICKY-a4mn9Q.jpg"
  },
  {
    "url": "https://nickystore.biz.id/anime/NICKY-R50CTB.jpg"
  },
  {
    "url": "https://nickystore.biz.id/anime/NICKY-IND0MU.jpg"
  },
  {
    "url": "https://nickystore.biz.id/anime/NICKY-7xJK2u.jpg"
  },
  {
    "url": "https://nickystore.biz.id/anime/NICKY-nMuIlw.jpg"
  },
  {
    "url": "https://nickystore.biz.id/anime/NICKY-gDi52X.jpg"
  },
  {
    "url": "https://nickystore.biz.id/anime/NICKY-bw3niQ.jpg"
  },
  {
    "url": "https://nickystore.biz.id/anime/NICKY-6Ej2wb.jpg"
  },
  {
    "url": "https://nickystore.biz.id/anime/NICKY-G7eyUo.jpg"
  },
  {
    "url": "https://nickystore.biz.id/anime/NICKY-ig06z3.jpg"
  },
  {
    "url": "https://nickystore.biz.id/anime/NICKY-DapoGx.jpg"
  },
  {
    "url": "https://nickystore.biz.id/anime/NICKY-cSVFOM.jpg"
  },
  {
    "url": "https://nickystore.biz.id/anime/NICKY-HyJPwM.jpg"
  },
  {
    "url": "https://nickystore.biz.id/anime/NICKY-e6ED3J.jpg"
  },
  {
    "url": "https://nickystore.biz.id/anime/NICKY-On2BU0.jpg"
  },
  {
    "url": "https://nickystore.biz.id/anime/NICKY-IThXPL.jpg"
  },
  {
    "url": "https://nickystore.biz.id/anime/NICKY-FYTzA3.jpg"
  },
  {
    "url": "https://nickystore.biz.id/anime/NICKY-yfjcp1.jpg"
  },
  {
    "url": "https://nickystore.biz.id/anime/NICKY-gjodv3.jpg"
  },
  {
    "url": "https://nickystore.biz.id/anime/NICKY-iNvAWE.jpg"
  },
  {
    "url": "https://nickystore.biz.id/anime/NICKY-uRoQ2D.jpg"
  },
  {
    "url": "https://nickystore.biz.id/anime/NICKY-0OSJyM.jpg"
  },
  {
    "url": "https://nickystore.biz.id/anime/NICKY-CzSeA9.jpg"
  },
  {
    "url": "https://nickystore.biz.id/anime/NICKY-NsUZqI.jpg"
  },
  {
    "url": "https://nickystore.biz.id/anime/NICKY-mFadUr.jpg"
  },
  {
    "url": "https://nickystore.biz.id/anime/NICKY-MsHYGn.jpg"
  },
  {
    "url": "https://nickystore.biz.id/anime/NICKY-Cph6jP.jpg"
  },
  {
    "url": "https://nickystore.biz.id/anime/NICKY-5dn6QL.jpg"
  },
  {
    "url": "https://nickystore.biz.id/anime/NICKY-rekONa.jpg"
  },
  {
    "url": "https://nickystore.biz.id/anime/NICKY-HMrBcN.jpg"
  },
  {
    "url": "https://nickystore.biz.id/anime/NICKY-YfNLWd.jpg"
  },
  {
    "url": "https://nickystore.biz.id/anime/NICKY-ERqsKX.jpg"
  },
  {
    "url": "https://nickystore.biz.id/anime/NICKY-P9Au5W.jpg"
  },
  {
    "url": "https://nickystore.biz.id/anime/NICKY-rE7ctP.jpg"
  },
  {
    "url": "https://nickystore.biz.id/anime/NICKY-UtmITG.jpg"
  },
  {
    "url": "https://nickystore.biz.id/anime/NICKY-BUtY5z.jpg"
  },
  {
    "url": "https://nickystore.biz.id/anime/NICKY-JosiXu.jpg"
  },
  {
    "url": "https://nickystore.biz.id/anime/NICKY-MEywf9.jpg"
  },
  {
    "url": "https://nickystore.biz.id/anime/NICKY-EtK9Ou.jpg"
  },
  {
    "url": "https://nickystore.biz.id/anime/NICKY-akNgVC.jpg"
  },
  {
    "url": "https://nickystore.biz.id/anime/NICKY-LucxtA.jpg"
  },
  {
    "url": "https://nickystore.biz.id/anime/NICKY-h9Ui58.jpg"
  },
  {
    "url": "https://nickystore.biz.id/anime/NICKY-gGAwj5.jpg"
  },
  {
    "url": "https://nickystore.biz.id/anime/NICKY-NpdZl7.jpg"
  },
  {
    "url": "https://nickystore.biz.id/anime/NICKY-HmWRbS.jpg"
  },
  {
    "url": "https://nickystore.biz.id/anime/NICKY-nxhCWg.jpg"
  },
  {
    "url": "https://nickystore.biz.id/anime/NICKY-d4rIBM.jpg"
  },
  {
    "url": "https://nickystore.biz.id/anime/NICKY-q1PUKX.jpg"
  },
  {
    "url": "https://nickystore.biz.id/anime/NICKY-XJ42If.jpg"
  },
  {
    "url": "https://nickystore.biz.id/anime/NICKY-9AI7ux.jpg"
  },
  {
    "url": "https://nickystore.biz.id/anime/NICKY-RzXCNd.jpg"
  },
  {
    "url": "https://nickystore.biz.id/anime/NICKY-nzOTRZ.jpg"
  },
  {
    "url": "https://nickystore.biz.id/anime/NICKY-fUzdGt.jpg"
  },
  {
    "url": "https://nickystore.biz.id/anime/NICKY-52Y7fu.jpg"
  },
  {
    "url": "https://nickystore.biz.id/anime/NICKY-s1R9XZ.jpg"
  },
  {
    "url": "https://nickystore.biz.id/anime/NICKY-6sKFCA.jpg"
  },
  {
    "url": "https://nickystore.biz.id/anime/NICKY-PM8Cqo.jpg"
  },
  {
    "url": "https://nickystore.biz.id/anime/NICKY-x7gCM4.jpg"
  },
  {
    "url": "https://nickystore.biz.id/anime/NICKY-VC4hIX.jpg"
  },
  {
    "url": "https://nickystore.biz.id/anime/NICKY-CbGtvJ.jpg"
  },
  {
    "url": "https://nickystore.biz.id/anime/NICKY-8LJluE.jpg"
  },
  {
    "url": "https://nickystore.biz.id/anime/NICKY-JvrKGE.jpg"
  },
  {
    "url": "https://nickystore.biz.id/anime/NICKY-VBcXIf.jpg"
  },
  {
    "url": "https://nickystore.biz.id/anime/NICKY-oyEMB0.jpg"
  },
  {
    "url": "https://nickystore.biz.id/anime/NICKY-An4Iax.jpg"
  },
  {
    "url": "https://nickystore.biz.id/anime/NICKY-G8NIY5.jpg"
  },
  {
    "url": "https://nickystore.biz.id/anime/NICKY-dq6gzU.jpg"
  },
  {
    "url": "https://nickystore.biz.id/anime/NICKY-8zPemN.jpg"
  },
  {
    "url": "https://nickystore.biz.id/anime/NICKY-X0WCwB.jpg"
  },
  {
    "url": "https://nickystore.biz.id/anime/NICKY-T5o0GE.jpg"
  },
  {
    "url": "https://nickystore.biz.id/anime/NICKY-BuwS9X.jpg"
  },
  {
    "url": "https://nickystore.biz.id/anime/NICKY-KbF5GQ.jpg"
  },
  {
    "url": "https://nickystore.biz.id/anime/NICKY-qtZrUm.jpg"
  },
  {
    "url": "https://nickystore.biz.id/anime/NICKY-bY5wJM.jpg"
  },
  {
    "url": "https://nickystore.biz.id/anime/NICKY-rd7lcx.jpg"
  },
  {
    "url": "https://nickystore.biz.id/anime/NICKY-udrb0q.jpg"
  },
  {
    "url": "https://nickystore.biz.id/anime/NICKY-l6npLR.jpg"
  },
  {
    "url": "https://nickystore.biz.id/anime/NICKY-g1IYph.jpg"
  },
  {
    "url": "https://p16-sign-va.tiktokcdn.com/tos-maliva-i-photomode-us/744f98a308614ae5a299c45b585ff1a4~tplv-photomode-image-v1:q70.jpeg?dr=14555&from=photomode.AWEME_DETAIL&ftpl=1&idc=maliva&ps=13740610&refresh_token=b337f380&s=AWEME_DETAIL&shcp=34ff8df6&shp=d05b14bd&t=4d5b0474&x-expires=1759561200&x-signature=OuuYyo3%2B5UspBe3dx%2BllmE86M9U%3D"
  },
  {
    "url": "https://p16-sign-va.tiktokcdn.com/tos-maliva-i-photomode-us/f5df53e56b64413d8e6c64d72279c5da~tplv-photomode-image-v1:q70.jpeg?dr=14555&from=photomode.AWEME_DETAIL&ftpl=1&idc=maliva&ps=13740610&refresh_token=2e7997cb&s=AWEME_DETAIL&shcp=34ff8df6&shp=d05b14bd&t=4d5b0474&x-expires=1759561200&x-signature=NHpXres5TIox7yW979A37JkFTRI%3D"
  },
  {
    "url": "https://p16-sign-va.tiktokcdn.com/tos-maliva-i-photomode-us/0a394b61ebd846dba91dd1df25dd3068~tplv-photomode-image-v1:q70.jpeg?dr=14555&from=photomode.AWEME_DETAIL&ftpl=1&idc=maliva&ps=13740610&refresh_token=6b29e5b2&s=AWEME_DETAIL&shcp=34ff8df6&shp=d05b14bd&t=4d5b0474&x-expires=1759561200&x-signature=53vzfMU1%2BWI6gmyFvwUF5yOx3kE%3D"
  },
  {
    "url": "https://p16-sign-va.tiktokcdn.com/tos-maliva-i-photomode-us/14576a3822e141de93263c5b409f0c14~tplv-photomode-image-v1:q70.jpeg?dr=14555&from=photomode.AWEME_DETAIL&ftpl=1&idc=maliva&ps=13740610&refresh_token=14593041&s=AWEME_DETAIL&shcp=34ff8df6&shp=d05b14bd&t=4d5b0474&x-expires=1759561200&x-signature=QISGh%2BoNVNgQeRBAORhkWNLGYRs%3D"
  },
  {
    "url": "https://p16-sign-va.tiktokcdn.com/tos-maliva-i-photomode-us/cea32b94c13447aea2cc3b5ffc97e882~tplv-photomode-image-v1:q70.jpeg?dr=14555&from=photomode.AWEME_DETAIL&ftpl=1&idc=maliva&ps=13740610&refresh_token=20138c23&s=AWEME_DETAIL&shcp=34ff8df6&shp=d05b14bd&t=4d5b0474&x-expires=1759561200&x-signature=d%2BjEVSsl7ukVwQ5TgWGDQqga5Ck%3D"
  },
  {
    "url": "https://p16-sign-va.tiktokcdn.com/tos-maliva-i-photomode-us/e3fec2361d4b49759f089b045070f2c3~tplv-photomode-image-v1:q70.jpeg?dr=14555&from=photomode.AWEME_DETAIL&ftpl=1&idc=maliva&ps=13740610&refresh_token=410bb5ac&s=AWEME_DETAIL&shcp=34ff8df6&shp=d05b14bd&t=4d5b0474&x-expires=1759561200&x-signature=hvzXi%2F5tOzhg0ULmlP%2B%2BLBQXqCU%3D"
  },
  {
    "url": "https://p16-sign-va.tiktokcdn.com/tos-maliva-i-photomode-us/97b4d0a48d2247529c9d6c4500ca6c0f~tplv-photomode-image-v1:q70.jpeg?dr=14555&from=photomode.AWEME_DETAIL&ftpl=1&idc=maliva&ps=13740610&refresh_token=2801a549&s=AWEME_DETAIL&shcp=34ff8df6&shp=d05b14bd&t=4d5b0474&x-expires=1759561200&x-signature=TVGBAAfJKC3IHoRhc1yBjjmqzs8%3D"
  },
  {
    "url": "https://p16-sign-va.tiktokcdn.com/tos-maliva-i-photomode-us/d8bdb3922fdf4ad1bb543805709f5536~tplv-photomode-image-v1:q70.jpeg?dr=14555&from=photomode.AWEME_DETAIL&ftpl=1&idc=maliva&ps=13740610&refresh_token=c19e0c5f&s=AWEME_DETAIL&shcp=34ff8df6&shp=d05b14bd&t=4d5b0474&x-expires=1759561200&x-signature=EyVJy2A%2BDCpYm2owGnBJohKKoPE%3D"
  },
  {
    "url": "https://p16-sign-va.tiktokcdn.com/tos-maliva-i-photomode-us/824dd4c768d1418fbf86f848cdca878e~tplv-photomode-image-v1:q70.jpeg?dr=14555&from=photomode.AWEME_DETAIL&ftpl=1&idc=maliva&ps=13740610&refresh_token=0b874706&s=AWEME_DETAIL&shcp=34ff8df6&shp=d05b14bd&t=4d5b0474&x-expires=1759561200&x-signature=%2BwBxbYcuMgNWGZUbOXjwKVfkScg%3D"
  },
  {
    "url": "https://p16-sign-va.tiktokcdn.com/tos-maliva-i-photomode-us/5759d194e50b4d0eafcff0bfd363354e~tplv-photomode-image-v1:q70.jpeg?dr=14555&from=photomode.AWEME_DETAIL&ftpl=1&idc=maliva&ps=13740610&refresh_token=702fc39d&s=AWEME_DETAIL&shcp=34ff8df6&shp=d05b14bd&t=4d5b0474&x-expires=1759561200&x-signature=q66ZFg7J0jbjhdrRcb2AwVnZ9XY%3D"
  },
  {
    "url": "https://p16-sign-va.tiktokcdn.com/tos-maliva-i-photomode-us/5a9a5108a8da4c8bacd2bd47d103f24a~tplv-photomode-image-v1:q70.jpeg?dr=14555&from=photomode.AWEME_DETAIL&ftpl=1&idc=maliva&ps=13740610&refresh_token=837e0731&s=AWEME_DETAIL&shcp=34ff8df6&shp=d05b14bd&t=4d5b0474&x-expires=1759561200&x-signature=2mCrWbwP2PJDa25yGcXnhZhNLtE%3D"
  },
  {
    "url": "https://p16-sign-va.tiktokcdn.com/tos-maliva-i-photomode-us/146867f1eb9944b6b43a877d310225e0~tplv-photomode-image-v1:q70.jpeg?dr=14555&from=photomode.AWEME_DETAIL&ftpl=1&idc=maliva&ps=13740610&refresh_token=45e7887e&s=AWEME_DETAIL&shcp=34ff8df6&shp=d05b14bd&t=4d5b0474&x-expires=1759561200&x-signature=7A6%2BMWHLBHu87%2FynwcDvMNcEVvQ%3D"
  },
  {
    "url": "https://p16-sign-va.tiktokcdn.com/tos-maliva-i-photomode-us/7463131c11dd4d64b972fcd82a4e5cec~tplv-photomode-image-v1:q70.jpeg?dr=14555&from=photomode.AWEME_DETAIL&ftpl=1&idc=maliva&ps=13740610&refresh_token=cf7a744c&s=AWEME_DETAIL&shcp=34ff8df6&shp=d05b14bd&t=4d5b0474&x-expires=1759561200&x-signature=0RhDsrHtIlN4ks4OIa7DINQTdJk%3D"
  },
  {
    "url": "https://p16-sign-va.tiktokcdn.com/tos-maliva-i-photomode-us/0475ae3408df42b8b89bc74bf579b6c4~tplv-photomode-image-v1:q70.jpeg?dr=14555&from=photomode.AWEME_DETAIL&ftpl=1&idc=maliva&ps=13740610&refresh_token=a14f0ab8&s=AWEME_DETAIL&shcp=34ff8df6&shp=d05b14bd&t=4d5b0474&x-expires=1759561200&x-signature=yGEsxPJD%2B8d0eXDGUimIMX9LP%2BE%3D"
  },
  {
    "url": "https://p16-sign-va.tiktokcdn.com/tos-maliva-i-photomode-us/6ebdab9e1aaa43b3834d5acdf37a3f4b~tplv-photomode-image-v1:q70.jpeg?dr=14555&from=photomode.AWEME_DETAIL&ftpl=1&idc=maliva&ps=13740610&refresh_token=6953dcb5&s=AWEME_DETAIL&shcp=34ff8df6&shp=d05b14bd&t=4d5b0474&x-expires=1759561200&x-signature=ZBfURRngOwRhVBnOaqYaWmtxx6U%3D"
  },
  {
    "url": "https://p16-sign-va.tiktokcdn.com/tos-maliva-i-photomode-us/db542f4e23b64c6e941df6a207f71a90~tplv-photomode-image-v1:q70.jpeg?dr=14555&from=photomode.AWEME_DETAIL&ftpl=1&idc=maliva&ps=13740610&refresh_token=76128244&s=AWEME_DETAIL&shcp=34ff8df6&shp=d05b14bd&t=4d5b0474&x-expires=1759557600&x-signature=ZDA4cf%2BmRj7dkierps3bnhDvprU%3D"
  },
  {
    "url": "https://p16-sign-va.tiktokcdn.com/tos-maliva-i-photomode-us/de49f442b382432bbd0e9d5ca2759311~tplv-photomode-image-v1:q70.jpeg?dr=14555&from=photomode.AWEME_DETAIL&ftpl=1&idc=maliva&ps=13740610&refresh_token=30142e8f&s=AWEME_DETAIL&shcp=34ff8df6&shp=d05b14bd&t=4d5b0474&x-expires=1759557600&x-signature=XT85NtUfm6hYvTXSTa5DnsQ7wLs%3D"
  },
  {
    "url": "https://p16-sign-va.tiktokcdn.com/tos-maliva-i-photomode-us/1876ca6de51a4c4f9877dbbe2183bb8a~tplv-photomode-image-v1:q70.jpeg?dr=14555&from=photomode.AWEME_DETAIL&ftpl=1&idc=maliva&ps=13740610&refresh_token=b0b99ff4&s=AWEME_DETAIL&shcp=34ff8df6&shp=d05b14bd&t=4d5b0474&x-expires=1759557600&x-signature=CoMXmfVvDsT7ccY%2FDzXeaVcl%2B6o%3D"
  },
  {
    "url": "https://p16-sign-va.tiktokcdn.com/tos-maliva-i-photomode-us/4c9ff27972a54bf891be6298dbb309f5~tplv-photomode-image-v1:q70.jpeg?dr=14555&from=photomode.AWEME_DETAIL&ftpl=1&idc=maliva&ps=13740610&refresh_token=5e49c3af&s=AWEME_DETAIL&shcp=34ff8df6&shp=d05b14bd&t=4d5b0474&x-expires=1759557600&x-signature=972acmS1o0D3%2BXN2VqtVugA%2BbG0%3D"
  },
  {
    "url": "https://p16-sign-va.tiktokcdn.com/tos-maliva-i-photomode-us/556138612615407caf1718bd95dca66b~tplv-photomode-image-v1:q70.jpeg?dr=14555&from=photomode.AWEME_DETAIL&ftpl=1&idc=maliva&ps=13740610&refresh_token=f1b40fab&s=AWEME_DETAIL&shcp=34ff8df6&shp=d05b14bd&t=4d5b0474&x-expires=1759557600&x-signature=Dxb63hElxhJnvEYI60H3GiYtsqo%3D"
  },
  {
    "url": "https://p16-sign-va.tiktokcdn.com/tos-maliva-i-photomode-us/fd3a1e0a68b04454b5d7172c1b9e2bed~tplv-photomode-image-v1:q70.jpeg?dr=14555&from=photomode.AWEME_DETAIL&ftpl=1&idc=maliva&ps=13740610&refresh_token=c44ed034&s=AWEME_DETAIL&shcp=34ff8df6&shp=d05b14bd&t=4d5b0474&x-expires=1759557600&x-signature=EDF7BnXcdH1BnkdQ27zm2mR6Tok%3D"
  },
  {
    "url": "https://p16-sign-va.tiktokcdn.com/tos-maliva-i-photomode-us/26b4a511ad394c7aa555bfa164ccfe2b~tplv-photomode-image-v1:q70.jpeg?dr=14555&from=photomode.AWEME_DETAIL&ftpl=1&idc=maliva&ps=13740610&refresh_token=b1563603&s=AWEME_DETAIL&shcp=34ff8df6&shp=d05b14bd&t=4d5b0474&x-expires=1759557600&x-signature=Wsz34liIKke4Yh%2BshuVi%2BWHGzX4%3D"
  },
  {
    "url": "https://p16-sign-va.tiktokcdn.com/tos-maliva-i-photomode-us/e86c323c414e4ac49a435df430125b8e~tplv-photomode-image-v1:q70.jpeg?dr=14555&from=photomode.AWEME_DETAIL&ftpl=1&idc=maliva&ps=13740610&refresh_token=1dc229a2&s=AWEME_DETAIL&shcp=34ff8df6&shp=d05b14bd&t=4d5b0474&x-expires=1759557600&x-signature=DEx742l5J6z9FTWcBUN0k8ytoU4%3D"
  },
  {
    "url": "https://p16-sign-va.tiktokcdn.com/tos-maliva-i-photomode-us/1aa4036b54314a7c81d0ffefe9fd1014~tplv-photomode-image-v1:q70.jpeg?dr=14555&from=photomode.AWEME_DETAIL&ftpl=1&idc=maliva&ps=13740610&refresh_token=738a7485&s=AWEME_DETAIL&shcp=34ff8df6&shp=d05b14bd&t=4d5b0474&x-expires=1759557600&x-signature=RtgefhTJzw%2Blu5hEpQFc7%2FQvBeY%3D"
  },
  {
    "url": "https://p16-sign-va.tiktokcdn.com/tos-maliva-i-photomode-us/369802b3f680486cb76465faf50217ef~tplv-photomode-image-v1:q70.jpeg?dr=14555&from=photomode.AWEME_DETAIL&ftpl=1&idc=maliva&ps=13740610&refresh_token=5000d2c4&s=AWEME_DETAIL&shcp=34ff8df6&shp=d05b14bd&t=4d5b0474&x-expires=1759557600&x-signature=lzUJIDldvc2a5mofoe9cJg%2BlTQs%3D"
  },
  {
    "url": "https://p16-sign-va.tiktokcdn.com/tos-maliva-i-photomode-us/67575c58ff524d6b8a016a5a13e1f1d5~tplv-photomode-image-v1:q70.jpeg?dr=14555&from=photomode.AWEME_DETAIL&ftpl=1&idc=maliva&ps=13740610&refresh_token=10607187&s=AWEME_DETAIL&shcp=34ff8df6&shp=d05b14bd&t=4d5b0474&x-expires=1759557600&x-signature=lHnVtBHFZV4nAMN9ANecVMeUdVg%3D"
  },
  {
    "url": "https://p16-sign-va.tiktokcdn.com/tos-maliva-i-photomode-us/5caf1f07550844d3aa515fc2286df4a9~tplv-photomode-image-v1:q70.jpeg?dr=14555&from=photomode.AWEME_DETAIL&ftpl=1&idc=maliva&ps=13740610&refresh_token=2ce906eb&s=AWEME_DETAIL&shcp=34ff8df6&shp=d05b14bd&t=4d5b0474&x-expires=1759557600&x-signature=FwxO2oWLP0h0VUeF%2B6XITwC7TDU%3D"
  },
  {
    "url": "https://p16-sign-va.tiktokcdn.com/tos-maliva-i-photomode-us/5d7a00c482c14810a6fa61ad4e66c54e~tplv-photomode-image-v1:q70.jpeg?dr=14555&from=photomode.AWEME_DETAIL&ftpl=1&idc=maliva&ps=13740610&refresh_token=1db12072&s=AWEME_DETAIL&shcp=34ff8df6&shp=d05b14bd&t=4d5b0474&x-expires=1759557600&x-signature=A7zgxKJwwbONRhLvRsnYaVnMxz8%3D"
  },
  {
    "url": "https://p16-sign-sg.tiktokcdn.com/tos-alisg-i-photomode-sg/62f74d87ff75477e9748833e7b0d16ef~tplv-photomode-image-v1:q70.jpeg?dr=1334&refresh_token=fd972d0a&x-expires=1759561200&x-signature=bbwjFBmCDJ9RqOBQF%2F%2Bm%2BNqbNbs%3D&t=5897f7ec&ps=b40d0ec8&shp=d05b14bd&shcp=1d1a97fc&idc=maliva&s=AWEME_DETAIL&biz_tag=tt_photomode&sc=image"
  },
  {
    "url": "https://p16-sign-sg.tiktokcdn.com/tos-alisg-i-photomode-sg/0dee47829f0c4f14a132c60be4867f49~tplv-photomode-image-v1:q70.jpeg?dr=1334&refresh_token=9a8cb165&x-expires=1759561200&x-signature=ZL1qa4ElhhIicL8It2god6jas%2FI%3D&t=5897f7ec&ps=b40d0ec8&shp=d05b14bd&shcp=1d1a97fc&idc=maliva&s=AWEME_DETAIL&biz_tag=tt_photomode&sc=image"
  },
  {
    "url": "https://p16-sign-sg.tiktokcdn.com/tos-alisg-i-photomode-sg/9dbdc44981a446f4861796c2147e2847~tplv-photomode-image-v1:q70.jpeg?dr=1334&refresh_token=50e21ef2&x-expires=1759561200&x-signature=l06TYErbgEo0JwkmMapwS9tkqsI%3D&t=5897f7ec&ps=b40d0ec8&shp=d05b14bd&shcp=1d1a97fc&idc=maliva&s=AWEME_DETAIL&biz_tag=tt_photomode&sc=image"
  },
  {
    "url": "https://p16-sign-sg.tiktokcdn.com/tos-alisg-i-photomode-sg/3e9a36ed04944ba69db191a5136eb1dc~tplv-photomode-image-v1:q70.jpeg?dr=1334&refresh_token=4537257e&x-expires=1759561200&x-signature=faoGCVExt0GQcZ%2BxBpPjY5OvlFc%3D&t=5897f7ec&ps=b40d0ec8&shp=d05b14bd&shcp=1d1a97fc&idc=maliva&s=AWEME_DETAIL&biz_tag=tt_photomode&sc=image"
  },
  {
    "url": "https://p16-sign-sg.tiktokcdn.com/tos-alisg-i-photomode-sg/a4ed84f815b44a5f9c4473f954bd1bd7~tplv-photomode-image-v1:q70.jpeg?dr=1334&refresh_token=a03b7d31&x-expires=1759561200&x-signature=HYb4mC1%2Fe3Ar1ebjbAfO2y6l59I%3D&t=5897f7ec&ps=b40d0ec8&shp=d05b14bd&shcp=1d1a97fc&idc=maliva&s=AWEME_DETAIL&biz_tag=tt_photomode&sc=image"
  },
  {
    "url": "https://p16-sign-sg.tiktokcdn.com/tos-alisg-i-photomode-sg/80ee97d357f443a6af86ad3544cd1003~tplv-photomode-image-v1:q70.jpeg?dr=1334&refresh_token=01e813b0&x-expires=1759561200&x-signature=Q0EunKEQL2PE%2BLks6sCvndef4l8%3D&t=5897f7ec&ps=b40d0ec8&shp=d05b14bd&shcp=1d1a97fc&idc=maliva&s=AWEME_DETAIL&biz_tag=tt_photomode&sc=image"
  },
  {
    "url": "https://p16-sign-va.tiktokcdn.com/tos-maliva-i-photomode-us/d086ab6f3fce482fb4970814ec8e5bb0~tplv-photomode-image-v1:q70.jpeg?dr=14555&from=photomode.AWEME_DETAIL&ftpl=1&idc=maliva&ps=13740610&refresh_token=9374b984&s=AWEME_DETAIL&shcp=34ff8df6&shp=d05b14bd&t=4d5b0474&x-expires=1759687200&x-signature=iUhl2%2FMidxTNKnG80mqieS6Y%2Fbs%3D"
  },
  {
    "url": "https://p16-sign-va.tiktokcdn.com/tos-maliva-i-photomode-us/fc9599c7271946089b691d60a7490c83~tplv-photomode-image-v1:q70.jpeg?dr=14555&from=photomode.AWEME_DETAIL&ftpl=1&idc=maliva&ps=13740610&refresh_token=a185d447&s=AWEME_DETAIL&shcp=34ff8df6&shp=d05b14bd&t=4d5b0474&x-expires=1759687200&x-signature=%2Fin9J1ea8Nt0QQapxFFN27bfMA8%3D"
  },
  {
    "url": "https://p16-sign-va.tiktokcdn.com/tos-maliva-i-photomode-us/132ce41fc37f441296188f9235b59357~tplv-photomode-image-v1:q70.jpeg?dr=14555&from=photomode.AWEME_DETAIL&ftpl=1&idc=maliva&ps=13740610&refresh_token=83a2922b&s=AWEME_DETAIL&shcp=34ff8df6&shp=d05b14bd&t=4d5b0474&x-expires=1759687200&x-signature=XlnW%2BsaT%2BhAgRKJ1F3xoz8IX3ZQ%3D"
  },
  {
    "url": "https://p16-sign-va.tiktokcdn.com/tos-maliva-i-photomode-us/67521c4bd039414ea89ad37eb16c3a37~tplv-photomode-image-v1:q70.jpeg?dr=14555&from=photomode.AWEME_DETAIL&ftpl=1&idc=maliva&ps=13740610&refresh_token=cecfaea8&s=AWEME_DETAIL&shcp=34ff8df6&shp=d05b14bd&t=4d5b0474&x-expires=1759687200&x-signature=B3DqCTrwwY3TbJOtQTROmmFXJ8E%3D"
  },
  {
    "url": "https://p16-sign-va.tiktokcdn.com/tos-maliva-i-photomode-us/36cc1482e55c4ce1a36c7117c6354db3~tplv-photomode-image-v1:q70.jpeg?dr=14555&from=photomode.AWEME_DETAIL&ftpl=1&idc=maliva&ps=13740610&refresh_token=e620ac19&s=AWEME_DETAIL&shcp=34ff8df6&shp=d05b14bd&t=4d5b0474&x-expires=1759687200&x-signature=UIA3Xp6vE5XzMfd9o%2FznX%2Bsip0g%3D"
  },
  {
    "url": "https://p16-sign-va.tiktokcdn.com/tos-maliva-i-photomode-us/a3ae1ab8ff1d452981c9d671248d509e~tplv-photomode-image-v1:q70.jpeg?dr=14555&from=photomode.AWEME_DETAIL&ftpl=1&idc=maliva&ps=13740610&refresh_token=69a8bf51&s=AWEME_DETAIL&shcp=34ff8df6&shp=d05b14bd&t=4d5b0474&x-expires=1759687200&x-signature=qYSEeak5m6ynw1qSgK%2FDN3%2FqUBo%3D"
  },
  {
    "url": "https://p16-sign-va.tiktokcdn.com/tos-maliva-i-photomode-us/89690c02f05f474ba4325ef11ea4a132~tplv-photomode-image-v1:q70.jpeg?dr=14555&from=photomode.AWEME_DETAIL&ftpl=1&idc=maliva&ps=13740610&refresh_token=c432bab9&s=AWEME_DETAIL&shcp=34ff8df6&shp=d05b14bd&t=4d5b0474&x-expires=1759687200&x-signature=EEcmLoTRN8oiau49GnBavVcEmK0%3D"
  },
  {
    "url": "https://p16-sign-va.tiktokcdn.com/tos-maliva-i-photomode-us/0c0de150d71c493f9d853d54a567df7d~tplv-photomode-image-v1:q70.jpeg?dr=14555&from=photomode.AWEME_DETAIL&ftpl=1&idc=maliva&ps=13740610&refresh_token=5757e7c2&s=AWEME_DETAIL&shcp=34ff8df6&shp=d05b14bd&t=4d5b0474&x-expires=1759687200&x-signature=W8teR88U8qR1zLuUCzlw%2Fm%2ByTis%3D"
  }
]